MANIFEST.in
README.md
setup.cfg
setup.py
tarbell/__init__.py
tarbell/app.py
tarbell/cli.py
tarbell/configure.py
tarbell/contextmanagers.py
tarbell/errors.py
tarbell/hooks.py
tarbell/oauth.py
tarbell/s3.py
tarbell/settings.py
tarbell/slughifi.py
tarbell/template.py
tarbell/utils.py
tarbell.egg-info/PKG-INFO
tarbell.egg-info/SOURCES.txt
tarbell.egg-info/dependency_links.txt
tarbell.egg-info/entry_points.txt
tarbell.egg-info/not-zip-safe
tarbell.egg-info/requires.txt
tarbell.egg-info/top_level.txt
tarbell/error_templates/404.html
tarbell/error_templates/_error.html
tarbell/error_templates/_googleapiclient.errors.HttpError.html
tarbell/error_templates/css/errors.css
tarbell/error_templates/error-img/ida-tarbell.jpg
tarbell/templates/tarbell_config.py.template