Metadata-Version: 1.0
Name: tarbell
Version: 1.0.9
Summary: A very simple content management system
Home-page: http://github.com/tarbell-project/tarbell
Author: Tarbell Project
Author-email: davideads@gmail.com
License: MIT
Keywords: Development Status :: 5 - Production/Stable,License :: OSI Approved :: MIT License,Operating System :: OS Independent,Programming Language :: Python,Topic :: Internet
Platform: UNKNOWN
